Workbook
Name List_Distribution: OFFSET(Lists!$A$3,0,0,MAX(COUNTA(Lists!$A$3:$A$1000),1),1)
Name List_MCInclude: OFFSET(Lists!$B$3,0,0,MAX(COUNTA(Lists!$B$3:$B$1000),1),1)
Name List_TimeImpact: OFFSET(Lists!$C$3,0,0,MAX(COUNTA(Lists!$C$3:$C$1000),1),1)
Name List_Recurrence: OFFSET(Lists!$D$3,0,0,MAX(COUNTA(Lists!$D$3:$D$1000),1),1)
Name List_Mode: OFFSET(Lists!$E$3,0,0,MAX(COUNTA(Lists!$E$3:$E$1000),1),1)
Name List_CGCode: OFFSET(Lists!$F$3,0,0,MAX(COUNTA(Lists!$F$3:$F$1000),1),1)
Name List_RBS_L1: OFFSET(Lists!$G$3,0,0,MAX(COUNTA(Lists!$G$3:$G$1000),1),1)
Name List_RBS_L2: OFFSET(Lists!$H$3,0,0,MAX(COUNTA(Lists!$H$3:$H$1000),1),1)
Name List_Package: OFFSET(Lists!$I$3,0,0,MAX(COUNTA(Lists!$I$3:$I$1000),1),1)
Name List_Factor: OFFSET(Lists!$J$3,0,0,MAX(COUNTA(Lists!$J$3:$J$1000),1),1)
Name MC_day_rate: 'MC_Params'!$C$15
Name Set_iterations: Settings!$B$1
Name Set_seed: Settings!$B$2
Name Set_view: Settings!$B$3
Name Set_risk_prefix: Settings!$B$4
Name Set_iterations_max: Settings!$B$5
Name Set_ContractVersion: Settings!$B$6
Name Set_Layer1_Enabled: Settings!$B$8
Name Out_ptable: Simulation!$A$2:$B$20
Name Out_scurve: Simulation!$D$2:$E$102
Name Corr_flag: Simulation!$H$1
Name Out_conv_halfwidth: Simulation!$H$3
Name Out_conv_pct: Simulation!$H$4
Name Out_triple: Simulation!$I$2:$L$20
Name Out_validation: Simulation!$N$2:$N$3
Name Grid_RiskRegister: 'Risk Register'!$A$1:$AE$39
Name Grid_Layer1_Base: 'Layer1_Base'!$A$1:$I$12
Name Grid_Layer1_Factors: 'Layer1_Factors'!$A$1:$F$15
Name Grid_Layer1_Allocation: 'Layer1_Allocation'!$A$1:$I$15
Name Grid_Layer1_Correlation: 'Layer1_Correlation'!$A$1:$H$11
Name Grid_Methodology: 'Methodology'!$A$1:$C$23
Name Grid_Mapping: 'Mapping'!$A$1:$F$11
Name Set_ProjectName: 'TOC & Instructions'!$B$58
Name Set_ProjectNumber: 'TOC & Instructions'!$B$59
Name Set_Client: 'TOC & Instructions'!$B$60
Name Set_PreparedBy: 'TOC & Instructions'!$B$61
Name Set_Revision: 'TOC & Instructions'!$B$62
Name Set_IssueDate: 'TOC & Instructions'!$B$63

Sheet TOC & Instructions
A1: Cost-QRA Register - project input document
A2: Scaffolded once by tools/register_scaffold.py, then this file is yours - fill it in, it is standalone. Re-scaffolding is never run against a live register.
A3: Register contract | B3: =Settings!B6 | C3: The engine checks this on every run and refuses on any mismatch. Shown here from Settings!B6, never typed twice.
A4: Tabs, in the order you fill them (auto-generated from the sheet inventory)
A5: Charts | B5: Chart dashboard - S-curve, P-curve, correlation sensitivity, tornado, EMV split. Generated by tools/register_polish.py. | C5: you fill
A6: Risk Register | B6: Event risks - cost + schedule three-point inputs, EMV. | C6: you fill
A7: EMV & Mode Analysis | B7: Deterministic Layer-1 EMV + Mode charts. | C7: you fill
A8: Simulation | B8: Model write-back: P-curve, S-curve, convergence. | C8: you fill
A9: Lists | B9: Cascade lists - edit here; the dropdowns follow. | C9: you fill
A10: Mapping | B10: P6/CPM binding for schedule (Time=Yes) risks. | C10: you fill
A11: MC_Params | B11: LIVE model parameters - TIC (C6), reporting P-level (C5), cascade params (C7:C14), CG coefficients and capex bases (C20:C31). MC_day_rate = MC_Params!$C$15 is part of the range contract. NOT legacy, and NOT safe to delete - Settings is the live RUN config, this is the live MODEL config. | C11: you fill
A12: Methodology | B12: CG correlation coefficients + Mode multipliers. | C12: you fill
A13: Settings | B13: Run settings (iterations/seed/view/prefix); the LIVE run-config surface. | C13: you fill
A14: Layer1_Base | B14: Layer-1 base estimate matrix. | C14: you fill
A15: Layer1_Factors | B15: Layer-1 risk factors. | C15: calculated
A16: Layer1_Allocation | B16: Layer-1 factor x WBS allocation. | C16: model writes
A17: Layer1_Correlation | B17: Layer-1 factor correlation matrix. | C17: reference
A18: Reference (xlwings) | B18: xlwings requirements + @script (paste-once).
A19: Handoff Prompt | B19: The presentation-layer brief, rendered from docs/polish_handoff.md.
A20: Build Log | B20: Presentation-layer spec - every formatting/chart change, in order. Rendered from config/polish_spec.yaml.
A21: Polish Inbox | B21: Append-only queue of PENDING presentation changes. The only place amendments are written.
A22: Reference (polish) | B22: The op vocabulary for raising a Polish Inbox row. Generated from the code.
A24: Cell-type legend
A25: input | B25: Blue font, unlocked - you fill this in.
A26: calc | B26: Black font, locked - a live Excel formula (do not overwrite).
A27: model | B27: Amber fill - written by the model each run; do not edit.
A28: model-read | B28: Thin blue border - the Python model reads this cell (may also be an input).
A29: Methodology defaults
B30: The Methodology tab ships with CG coefficients defaulted to 0.5 - review / elicit per project. Mode multipliers (Series 1.0 / Hybrid 0.5 / Parallel 0.0) are locked methodology constants.
A32: Layer 1 - deterministic factor model (optional)
B33: The four Layer1_* tabs and the EMV & Mode Analysis tab are STANDARD on every register, but Layer 1 ships OFF: Settings!Set_Layer1_Enabled = FALSE, so the blank grids have NIL impact and the register reads exactly as a cost-only project. The grids ship at their real shape, blank: Layer1_Base is 12 placeholder WBS rows x 8 resource columns, in $M; Layer1_Allocation is 25 factor rows x the same WBS columns; Layer1_Correlation is a 25-factor lower triangle. To use Layer 1: (1) on Layer1_Base rename the WBS rows you need and type each row's $M by column, then the Declared_Total. A row with no numbers is ignored, so type 0 for a genuine zero. (2) On Layer1_Allocation rename the same WBS columns to match Layer1_Base EXACTLY - the model matches the two by name and refuses a mismatch; unused placeholder columns can stay. List your factors on Layer1_Factors (pick names from the dropdown) and tick their WBS cells with x. (3) On Layer1_Correlation type the correlated factor names across row 4 and down column A in the same order, and the coefficients in the blue lower triangle; grey cells are never read, and a blank pair means 0. (4) ONLY THEN set Set_Layer1_Enabled = TRUE. Turning Layer 1 on before the grids are filled is refused with a message naming the tab. The EMV & Mode Analysis tab (totals + charts) populates from the register EMV columns whenever the register is filled or a run happens. Leave the flag FALSE to keep Layer 1 off. A project needing more rows regenerates with build_template(n_layer1_wbs_rows=, n_layer1_factors=).
A35: Sheet protection (REG04)
B36: The machine tabs are protected (no password): input cells are unlocked, the contract cells + formulas are locked, and the workbook structure is locked so tabs cannot be deleted/reordered. This guards against accidental edits - it does NOT stop you deleting a named range, so run Validate Contract after any structural edit. That is a task-pane item, not a button on any sheet, and it exists only after activation - see 'Running a simulation' below. To make deliberate changes, Review > Unprotect Sheet.
A38: Running a simulation
B39: STEP 1 - ACTIVATION, ONCE PER WORKBOOK, AND IT IS A SPECIALIST'S TASK (R-8). As it ships this workbook holds no code and no buttons: there is nothing to press and nothing is broken. A risk specialist installs the xlwings Lite add-in, adds numpy and scipy to its Environment, generates the model script by running tools/make_qra_xlwings.py in the repository, and pastes the result into the xlwings Lite editor. The Reference (xlwings) tab carries the requirements and a readable copy of the entry points. Until this is done, no simulation can run.
B40: STEP 2 - FILL THE REGISTER. Enter one risk per row on Risk Register from row 5. Blue cells are yours; the dropdowns are driven by the Lists tab. You can sort and filter the register with the sheet protected. You cannot INSERT a row: Excel inserts a whole row and the EMV columns are locked calc cells, so a 41st risk means Review > Unprotect Sheet (a specialist's step) or a register regenerated at a higher row count. Set the run controls on Settings (iterations, seed, view). If you are dollarising schedule delay, put the day rate on MC_Params - it is blank as shipped, and every schedule-dollar figure stays zero until it is filled.
B41: STEP 3 - RUN, from the xlwings Lite task pane on the right. These are task-pane items, NOT buttons on any sheet: 'Run Simulation' (the interactive count from Settings), 'Run Simulation 100k' (the deliverable count), and 'Validate Contract' (self-checks the named ranges and the version, writing PASS or FAIL). Results land on the Simulation tab, which is amber - written by the model, do not edit.
B42: WITHOUT ACTIVATION you can still do real work: fill the register and read the live expected-value totals and charts on Summary and EMV & Mode Analysis. Those are ordinary Excel formulas and need no simulation. What activation adds is the Monte-Carlo run.
B43: SPECIALIST TABS. The four Layer1_* tabs are Tier-2: they need an elicited factor model and are optional (see Layer 1 above). Simulation and Out_* are written by the model. A generalist needs none of them.
A45: Units, basis and formats - read before filling
B46: UNITS. Risk Register costs are dollars ($); time is working days. Probability and Probability (Time) are FRACTIONS between 0 and 1: 0.45 means 45%, and entering 45 makes the risk fire on every iteration, silently. Layer-1 base values and Declared_Total are $M.
B47: BASIS. Every figure is contingency at base date, before escalation. Escalation (GN4) is applied downstream to reach an outturn figure, never in this workbook.
B48: THREE-POINT INPUTS. Optimistic / Most Likely / Pessimistic are read by the Distribution column. Triangular and PERT treat Optimistic and Pessimistic as absolute bounds. Lognormal treats them as roughly P10 and P90 with a tail beyond Pessimistic, and Most Likely as the median. Binary fires the Most Likely value; Binary/PERT draws a PERT when it fires. The time three-points follow the same rule, in working days.
B49: COMPOSITION. Each iteration fires each risk with MC Include = Yes against its Probability and sums the sampled costs - MC Include is the switch, not Risk Status. A Time Impact = Yes risk shares one severity draw between its cost and its delay, so the two move together. When Layer 1 is on, each base cell is multiplied by (1 + factor) for every factor bound to it (rows via Layer1_Allocation, columns via Column_Scope) - the factor three-points are proportional deltas, 0.05 meaning +5% - and the result is added to the event total.
B50: RECORDED, NOT READ. Effectiveness_Confidence, Default_Mapping_Confidence and Assignment_Confidence are kept for a reviewer and never used by the engine: any scale, or blank.
B51: WHERE THE REST IS. Each fillable sheet carries its notes above its headers and each column's format on its header cell (hover). How to run: 'Running a simulation' above. What the colours mean: the legend above.
A57: Project identity
A58: Project name | B58: Tropic Ridge Wind Farm
A59: Project number | B59: TR-BOP-001
A60: Client | B60: Wind Farm Owner
A61: Prepared by | B61: CBL Analytics
A62: Revision | B62: A
A63: Issue date

Sheet Charts
A1: ="Cost-QRA Charts — "&Set_ProjectName&" ("&Set_ProjectNumber&")" | R1: Tornado helper — top 15 risks by cost EMV (formula-driven) | X1: S-curve helper (X = cost, Y = cumulative probability) | AA1: P-curve helper (text categories) | AD1: Correlation sensitivity helper (text categories)
A2: All charts are driven by live ranges on Simulation / EMV & Mode Analysis. Re-run the model and these refresh. Generated by tools/register_polish.py — do not hand-edit. | R2: Rank | S2: Risk | T2: Cost EMV ($) | V2: Tie-break key | X2: Cost ($) | Y2: Cumulative probability | AA2: P-level | AB2: Cost ($) | AD2: P-level | AE2: ρ = 0 (independent) | AF2: Elicited ρ | AG2: ρ = 1 (fully correlated)
R3: 1 | S3: =INDEX('Risk Register'!$C$5:$C$39,MATCH(LARGE($V$3:$V$37,$R3),$V$3:$V$37,0)) | T3: =INDEX('EMV & Mode Analysis'!$B$12:$B$46,MATCH(LARGE($V$3:$V$37,$R3),$V$3:$V$37,0)) | V3: ='EMV & Mode Analysis'!B12-ROW()/1000000 | X3: =Simulation!E2 | Y3: =Simulation!D2 | AA3: ="P"&Simulation!A2 | AB3: =Simulation!B2 | AD3: ="P"&Simulation!I2 | AE3: =Simulation!J2 | AF3: =Simulation!K2 | AG3: =Simulation!L2
R4: =R3+1 | S4: =INDEX('Risk Register'!$C$5:$C$39,MATCH(LARGE($V$3:$V$37,$R4),$V$3:$V$37,0)) | T4: =INDEX('EMV & Mode Analysis'!$B$12:$B$46,MATCH(LARGE($V$3:$V$37,$R4),$V$3:$V$37,0)) | V4: ='EMV & Mode Analysis'!B13-ROW()/1000000 | X4: =Simulation!E3 | Y4: =Simulation!D3 | AA4: ="P"&Simulation!A3 | AB4: =Simulation!B3 | AD4: ="P"&Simulation!I3 | AE4: =Simulation!J3 | AF4: =Simulation!K3 | AG4: =Simulation!L3
R5: =R4+1 | S5: =INDEX('Risk Register'!$C$5:$C$39,MATCH(LARGE($V$3:$V$37,$R5),$V$3:$V$37,0)) | T5: =INDEX('EMV & Mode Analysis'!$B$12:$B$46,MATCH(LARGE($V$3:$V$37,$R5),$V$3:$V$37,0)) | V5: ='EMV & Mode Analysis'!B14-ROW()/1000000 | X5: =Simulation!E4 | Y5: =Simulation!D4 | AA5: ="P"&Simulation!A4 | AB5: =Simulation!B4 | AD5: ="P"&Simulation!I4 | AE5: =Simulation!J4 | AF5: =Simulation!K4 | AG5: =Simulation!L4
R6: =R5+1 | S6: =INDEX('Risk Register'!$C$5:$C$39,MATCH(LARGE($V$3:$V$37,$R6),$V$3:$V$37,0)) | T6: =INDEX('EMV & Mode Analysis'!$B$12:$B$46,MATCH(LARGE($V$3:$V$37,$R6),$V$3:$V$37,0)) | V6: ='EMV & Mode Analysis'!B15-ROW()/1000000 | X6: =Simulation!E5 | Y6: =Simulation!D5 | AA6: ="P"&Simulation!A5 | AB6: =Simulation!B5 | AD6: ="P"&Simulation!I5 | AE6: =Simulation!J5 | AF6: =Simulation!K5 | AG6: =Simulation!L5
R7: =R6+1 | S7: =INDEX('Risk Register'!$C$5:$C$39,MATCH(LARGE($V$3:$V$37,$R7),$V$3:$V$37,0)) | T7: =INDEX('EMV & Mode Analysis'!$B$12:$B$46,MATCH(LARGE($V$3:$V$37,$R7),$V$3:$V$37,0)) | V7: ='EMV & Mode Analysis'!B16-ROW()/1000000 | X7: =Simulation!E6 | Y7: =Simulation!D6 | AA7: ="P"&Simulation!A6 | AB7: =Simulation!B6 | AD7: ="P"&Simulation!I6 | AE7: =Simulation!J6 | AF7: =Simulation!K6 | AG7: =Simulation!L6
R8: =R7+1 | S8: =INDEX('Risk Register'!$C$5:$C$39,MATCH(LARGE($V$3:$V$37,$R8),$V$3:$V$37,0)) | T8: =INDEX('EMV & Mode Analysis'!$B$12:$B$46,MATCH(LARGE($V$3:$V$37,$R8),$V$3:$V$37,0)) | V8: ='EMV & Mode Analysis'!B17-ROW()/1000000 | X8: =Simulation!E7 | Y8: =Simulation!D7 | AA8: ="P"&Simulation!A7 | AB8: =Simulation!B7 | AD8: ="P"&Simulation!I7 | AE8: =Simulation!J7 | AF8: =Simulation!K7 | AG8: =Simulation!L7
R9: =R8+1 | S9: =INDEX('Risk Register'!$C$5:$C$39,MATCH(LARGE($V$3:$V$37,$R9),$V$3:$V$37,0)) | T9: =INDEX('EMV & Mode Analysis'!$B$12:$B$46,MATCH(LARGE($V$3:$V$37,$R9),$V$3:$V$37,0)) | V9: ='EMV & Mode Analysis'!B18-ROW()/1000000 | X9: =Simulation!E8 | Y9: =Simulation!D8 | AA9: ="P"&Simulation!A8 | AB9: =Simulation!B8 | AD9: ="P"&Simulation!I8 | AE9: =Simulation!J8 | AF9: =Simulation!K8 | AG9: =Simulation!L8
R10: =R9+1 | S10: =INDEX('Risk Register'!$C$5:$C$39,MATCH(LARGE($V$3:$V$37,$R10),$V$3:$V$37,0)) | T10: =INDEX('EMV & Mode Analysis'!$B$12:$B$46,MATCH(LARGE($V$3:$V$37,$R10),$V$3:$V$37,0)) | V10: ='EMV & Mode Analysis'!B19-ROW()/1000000 | X10: =Simulation!E9 | Y10: =Simulation!D9 | AA10: ="P"&Simulation!A9 | AB10: =Simulation!B9 | AD10: ="P"&Simulation!I9 | AE10: =Simulation!J9 | AF10: =Simulation!K9 | AG10: =Simulation!L9
R11: =R10+1 | S11: =INDEX('Risk Register'!$C$5:$C$39,MATCH(LARGE($V$3:$V$37,$R11),$V$3:$V$37,0)) | T11: =INDEX('EMV & Mode Analysis'!$B$12:$B$46,MATCH(LARGE($V$3:$V$37,$R11),$V$3:$V$37,0)) | V11: ='EMV & Mode Analysis'!B20-ROW()/1000000 | X11: =Simulation!E10 | Y11: =Simulation!D10 | AA11: ="P"&Simulation!A10 | AB11: =Simulation!B10 | AD11: ="P"&Simulation!I10 | AE11: =Simulation!J10 | AF11: =Simulation!K10 | AG11: =Simulation!L10
R12: =R11+1 | S12: =INDEX('Risk Register'!$C$5:$C$39,MATCH(LARGE($V$3:$V$37,$R12),$V$3:$V$37,0)) | T12: =INDEX('EMV & Mode Analysis'!$B$12:$B$46,MATCH(LARGE($V$3:$V$37,$R12),$V$3:$V$37,0)) | V12: ='EMV & Mode Analysis'!B21-ROW()/1000000 | X12: =Simulation!E11 | Y12: =Simulation!D11 | AA12: ="P"&Simulation!A11 | AB12: =Simulation!B11 | AD12: ="P"&Simulation!I11 | AE12: =Simulation!J11 | AF12: =Simulation!K11 | AG12: =Simulation!L11
R13: =R12+1 | S13: =INDEX('Risk Register'!$C$5:$C$39,MATCH(LARGE($V$3:$V$37,$R13),$V$3:$V$37,0)) | T13: =INDEX('EMV & Mode Analysis'!$B$12:$B$46,MATCH(LARGE($V$3:$V$37,$R13),$V$3:$V$37,0)) | V13: ='EMV & Mode Analysis'!B22-ROW()/1000000 | X13: =Simulation!E12 | Y13: =Simulation!D12 | AA13: ="P"&Simulation!A12 | AB13: =Simulation!B12 | AD13: ="P"&Simulation!I12 | AE13: =Simulation!J12 | AF13: =Simulation!K12 | AG13: =Simulation!L12
R14: =R13+1 | S14: =INDEX('Risk Register'!$C$5:$C$39,MATCH(LARGE($V$3:$V$37,$R14),$V$3:$V$37,0)) | T14: =INDEX('EMV & Mode Analysis'!$B$12:$B$46,MATCH(LARGE($V$3:$V$37,$R14),$V$3:$V$37,0)) | V14: ='EMV & Mode Analysis'!B23-ROW()/1000000 | X14: =Simulation!E13 | Y14: =Simulation!D13 | AA14: ="P"&Simulation!A13 | AB14: =Simulation!B13 | AD14: ="P"&Simulation!I13 | AE14: =Simulation!J13 | AF14: =Simulation!K13 | AG14: =Simulation!L13
R15: =R14+1 | S15: =INDEX('Risk Register'!$C$5:$C$39,MATCH(LARGE($V$3:$V$37,$R15),$V$3:$V$37,0)) | T15: =INDEX('EMV & Mode Analysis'!$B$12:$B$46,MATCH(LARGE($V$3:$V$37,$R15),$V$3:$V$37,0)) | V15: ='EMV & Mode Analysis'!B24-ROW()/1000000 | X15: =Simulation!E14 | Y15: =Simulation!D14 | AA15: ="P"&Simulation!A14 | AB15: =Simulation!B14 | AD15: ="P"&Simulation!I14 | AE15: =Simulation!J14 | AF15: =Simulation!K14 | AG15: =Simulation!L14
... R17: =R16+1 | S17: =INDEX('Risk Register'!$C$5:$C$39,MATCH(LARGE($V$3:$V$37,$R17),$V$3:$V$37,0)) | T17: =INDEX('EMV & Mode Analysis'!$B$12:$B$46,MATCH(LARGE($V$3:$V$37,$R17),$V$3:$V$37,0)) | V17: ='EMV & Mode Analysis'!B26-ROW()/1000000 | X17: =Simulation!E16 | Y17: =Simulation!D16 | AA17: ="P"&Simulation!A16 | AB17: =Simulation!B16 | AD17: ="P"&Simulation!I16 | AE17: =Simulation!J16 | AF17: =Simulation!K16 | AG17: =Simulation!L16
V18: ='EMV & Mode Analysis'!B27-ROW()/1000000 | X18: =Simulation!E17 | Y18: =Simulation!D17 | AA18: ="P"&Simulation!A17 | AB18: =Simulation!B17 | AD18: ="P"&Simulation!I17 | AE18: =Simulation!J17 | AF18: =Simulation!K17 | AG18: =Simulation!L17
V19: ='EMV & Mode Analysis'!B28-ROW()/1000000 | X19: =Simulation!E18 | Y19: =Simulation!D18 | AA19: ="P"&Simulation!A18 | AB19: =Simulation!B18 | AD19: ="P"&Simulation!I18 | AE19: =Simulation!J18 | AF19: =Simulation!K18 | AG19: =Simulation!L18
V20: ='EMV & Mode Analysis'!B29-ROW()/1000000 | X20: =Simulation!E19 | Y20: =Simulation!D19 | AA20: ="P"&Simulation!A19 | AB20: =Simulation!B19 | AD20: ="P"&Simulation!I19 | AE20: =Simulation!J19 | AF20: =Simulation!K19 | AG20: =Simulation!L19
V21: ='EMV & Mode Analysis'!B30-ROW()/1000000 | X21: =Simulation!E20 | Y21: =Simulation!D20 | AA21: ="P"&Simulation!A20 | AB21: =Simulation!B20 | AD21: ="P"&Simulation!I20 | AE21: =Simulation!J20 | AF21: =Simulation!K20 | AG21: =Simulation!L20
V22: ='EMV & Mode Analysis'!B31-ROW()/1000000 | X22: =Simulation!E21 | Y22: =Simulation!D21
V23: ='EMV & Mode Analysis'!B32-ROW()/1000000 | X23: =Simulation!E22 | Y23: =Simulation!D22
V24: ='EMV & Mode Analysis'!B33-ROW()/1000000 | X24: =Simulation!E23 | Y24: =Simulation!D23
V25: ='EMV & Mode Analysis'!B34-ROW()/1000000 | X25: =Simulation!E24 | Y25: =Simulation!D24
V26: ='EMV & Mode Analysis'!B35-ROW()/1000000 | X26: =Simulation!E25 | Y26: =Simulation!D25
V27: ='EMV & Mode Analysis'!B36-ROW()/1000000 | X27: =Simulation!E26 | Y27: =Simulation!D26
V28: ='EMV & Mode Analysis'!B37-ROW()/1000000 | X28: =Simulation!E27 | Y28: =Simulation!D27
V29: ='EMV & Mode Analysis'!B38-ROW()/1000000 | X29: =Simulation!E28 | Y29: =Simulation!D28
V30: ='EMV & Mode Analysis'!B39-ROW()/1000000 | X30: =Simulation!E29 | Y30: =Simulation!D29
V31: ='EMV & Mode Analysis'!B40-ROW()/1000000 | X31: =Simulation!E30 | Y31: =Simulation!D30
V32: ='EMV & Mode Analysis'!B41-ROW()/1000000 | X32: =Simulation!E31 | Y32: =Simulation!D31
V33: ='EMV & Mode Analysis'!B42-ROW()/1000000 | X33: =Simulation!E32 | Y33: =Simulation!D32
... V37: ='EMV & Mode Analysis'!B46-ROW()/1000000 | X37: =Simulation!E36 | Y37: =Simulation!D36
X38: =Simulation!E37 | Y38: =Simulation!D37
X39: =Simulation!E38 | Y39: =Simulation!D38
X40: =Simulation!E39 | Y40: =Simulation!D39
X41: =Simulation!E40 | Y41: =Simulation!D40
X42: =Simulation!E41 | Y42: =Simulation!D41
X43: =Simulation!E42 | Y43: =Simulation!D42
X44: =Simulation!E43 | Y44: =Simulation!D43
X45: =Simulation!E44 | Y45: =Simulation!D44
X46: =Simulation!E45 | Y46: =Simulation!D45
X47: =Simulation!E46 | Y47: =Simulation!D46
X48: =Simulation!E47 | Y48: =Simulation!D47
X49: =Simulation!E48 | Y49: =Simulation!D48
... X103: =Simulation!E102 | Y103: =Simulation!D102

Sheet Risk Register
N3: Contingent Risk Cost | T3: Time (Working Days) | Z3: Analyst / Derived (deterministic Layer 1) | AE3: Schedule Binding (P6-ready)
A4: Risk ID | B4: Risk Status | C4: Risk Description | D4: Package | E4: RBS LVL 1 | F4: RBS LVL 2 | G4: MC Include | H4: Distribution | I4: Correlation Group | J4: Recurrence Type | K4: Causes | L4: Consequences | M4: Existing Controls | N4: Cost Impact | O4: Probability | P4: Optimistic ($) | Q4: Most Likely ($) | R4: Pessimistic ($) | S4: Basis of Estimate | T4: Time Impact | U4: Probability (Time) | V4: Optimistic (days) | W4: Most Likely (days) | X4: Pessimistic (days) | Y4: Basis of Estimate | Z4: Mode | AA4: Impact_Basis | AB4: EMV_cost ($) | AC4: EMV_sched_days | AD4: EMV_sched_dollars ($) | AE4: Schedule Activity ID (P6)
A5: WT-001 | B5: Open | C5: Turbine foundation rework | D5: EPC Contractor | E5: Civil & Earthworks | F5: Foundations | G5: Yes | H5: PERT | I5: CG01 | K5: synthetic cause | L5: synthetic consequence | M5: synthetic controls | N5: Yes | O5: 0.45 | P5: 100000 | Q5: 300000 | R5: 700000 | S5: Wind Farm Beta capex basis | T5: Yes | U5: 0.45 | V5: 5 | W5: 12 | X5: 24 | Y5: Synthetic | Z5: Series | AA5: per_occurrence | AB5: =IF(O5="","",O5*IF(OR(LOWER(H5)="pert",LOWER(H5)="binary/pert"),(P5+4*Q5+R5)/6,IF(LOWER(H5)="binary",Q5,IF(LOWER(H5)="lognormal",IF(Q5<=0,0,IF(OR(R5<=P5,R5<=0,P5<=0),ABS(Q5),Q5*EXP((MAX((LN(R5)-LN(P5))/(2*1.2816),0.01)^2)/2))),(P5+Q5+R5)/3)))) | AC5: =IF(OR(T5<>"Yes",U5=""),0,U5*(V5+4*W5+X5)/6*IFERROR(INDEX(Methodology!$B$2:$B$20,MATCH(Z5,Methodology!$A$2:$A$20,0)),0)) | AD5: =AC5*MC_day_rate
A6: WT-002 | B6: Open | C6: Access road wet-weather damage | D6: EPC Contractor | E6: Civil & Earthworks | F6: Roads | G6: Yes | H6: Triangular | I6: CG01 | J6: Single | K6: synthetic cause | L6: synthetic consequence | M6: synthetic controls | N6: Yes | O6: 0.5 | P6: 60000 | Q6: 180000 | R6: 500000 | S6: Wind Farm Beta capex basis | T6: Yes | U6: 0.5 | V6: 3 | W6: 7 | X6: 16 | Y6: Synthetic | Z6: Hybrid | AA6: per_occurrence | AB6: =IF(O6="","",O6*IF(OR(LOWER(H6)="pert",LOWER(H6)="binary/pert"),(P6+4*Q6+R6)/6,IF(LOWER(H6)="binary",Q6,IF(LOWER(H6)="lognormal",IF(Q6<=0,0,IF(OR(R6<=P6,R6<=0,P6<=0),ABS(Q6),Q6*EXP((MAX((LN(R6)-LN(P6))/(2*1.2816),0.01)^2)/2))),(P6+Q6+R6)/3)))) | AC6: =IF(OR(T6<>"Yes",U6=""),0,U6*(V6+4*W6+X6)/6*IFERROR(INDEX(Methodology!$B$2:$B$20,MATCH(Z6,Methodology!$A$2:$A$20,0)),0)) | AD6: =AC6*MC_day_rate
A7: WT-003 | B7: Open | C7: Unforeseen ground conditions | D7: EPC Contractor | E7: Civil & Earthworks | F7: Earthworks | G7: Yes | H7: Lognormal | I7: CG01 | K7: synthetic cause | L7: synthetic consequence | M7: synthetic controls | N7: Yes | O7: 0.35 | P7: 150000 | Q7: 400000 | R7: 1100000 | S7: Wind Farm Beta capex basis | T7: No | U7: 0 | V7: 0 | W7: 0 | X7: 0 | Y7: Synthetic | AA7: per_occurrence | AB7: =IF(O7="","",O7*IF(OR(LOWER(H7)="pert",LOWER(H7)="binary/pert"),(P7+4*Q7+R7)/6,IF(LOWER(H7)="binary",Q7,IF(LOWER(H7)="lognormal",IF(Q7<=0,0,IF(OR(R7<=P7,R7<=0,P7<=0),ABS(Q7),Q7*EXP((MAX((LN(R7)-LN(P7))/(2*1.2816),0.01)^2)/2))),(P7+Q7+R7)/3)))) | AC7: =IF(OR(T7<>"Yes",U7=""),0,U7*(V7+4*W7+X7)/6*IFERROR(INDEX(Methodology!$B$2:$B$20,MATCH(Z7,Methodology!$A$2:$A$20,0)),0)) | AD7: =AC7*MC_day_rate
A8: WT-004 | B8: Open | C8: Hardstand settlement | D8: EPC Contractor | E8: Civil & Earthworks | F8: Hardstands | G8: Yes | H8: PERT | I8: CG01 | K8: synthetic cause | L8: synthetic consequence | M8: synthetic controls | N8: Yes | O8: 0.25 | P8: 40000 | Q8: 120000 | R8: 350000 | S8: Wind Farm Beta capex basis | T8: No | U8: 0 | V8: 0 | W8: 0 | X8: 0 | Y8: Synthetic | AA8: per_occurrence | AB8: =IF(O8="","",O8*IF(OR(LOWER(H8)="pert",LOWER(H8)="binary/pert"),(P8+4*Q8+R8)/6,IF(LOWER(H8)="binary",Q8,IF(LOWER(H8)="lognormal",IF(Q8<=0,0,IF(OR(R8<=P8,R8<=0,P8<=0),ABS(Q8),Q8*EXP((MAX((LN(R8)-LN(P8))/(2*1.2816),0.01)^2)/2))),(P8+Q8+R8)/3)))) | AC8: =IF(OR(T8<>"Yes",U8=""),0,U8*(V8+4*W8+X8)/6*IFERROR(INDEX(Methodology!$B$2:$B$20,MATCH(Z8,Methodology!$A$2:$A$20,0)),0)) | AD8: =AC8*MC_day_rate
A9: WT-005 | B9: Open | C9: Bulk earthworks quantity overrun | D9: EPC Contractor | E9: Civil & Earthworks | F9: Earthworks | G9: Yes | H9: Triangular | I9: CG01 | K9: synthetic cause | L9: synthetic consequence | M9: synthetic controls | N9: Yes | O9: 0.55 | P9: 80000 | Q9: 220000 | R9: 480000 | S9: Wind Farm Beta capex basis | T9: No | U9: 0 | V9: 0 | W9: 0 | X9: 0 | Y9: Synthetic | AA9: per_occurrence | AB9: =IF(O9="","",O9*IF(OR(LOWER(H9)="pert",LOWER(H9)="binary/pert"),(P9+4*Q9+R9)/6,IF(LOWER(H9)="binary",Q9,IF(LOWER(H9)="lognormal",IF(Q9<=0,0,IF(OR(R9<=P9,R9<=0,P9<=0),ABS(Q9),Q9*EXP((MAX((LN(R9)-LN(P9))/(2*1.2816),0.01)^2)/2))),(P9+Q9+R9)/3)))) | AC9: =IF(OR(T9<>"Yes",U9=""),0,U9*(V9+4*W9+X9)/6*IFERROR(INDEX(Methodology!$B$2:$B$20,MATCH(Z9,Methodology!$A$2:$A$20,0)),0)) | AD9: =AC9*MC_day_rate
A10: WT-006 | B10: Open | C10: Drainage & culvert rework | D10: EPC Contractor | E10: Civil & Earthworks | F10: Drainage | G10: Yes | H10: PERT | I10: CG01 | K10: synthetic cause | L10: synthetic consequence | M10: synthetic controls | N10: Yes | O10: 0.3 | P10: 50000 | Q10: 140000 | R10: 300000 | S10: Wind Farm Beta capex basis | T10: No | U10: 0 | V10: 0 | W10: 0 | X10: 0 | Y10: Synthetic | AA10: per_occurrence | AB10: =IF(O10="","",O10*IF(OR(LOWER(H10)="pert",LOWER(H10)="binary/pert"),(P10+4*Q10+R10)/6,IF(LOWER(H10)="binary",Q10,IF(LOWER(H10)="lognormal",IF(Q10<=0,0,IF(OR(R10<=P10,R10<=0,P10<=0),ABS(Q10),Q10*EXP((MAX((LN(R10)-LN(P10))/(2*1.2816),0.01)^2)/2))),(P10+Q10+R10)/3)))) | AC10: =IF(OR(T10<>"Yes",U10=""),0,U10*(V10+4*W10+X10)/6*IFERROR(INDEX(Methodology!$B$2:$B$20,MATCH(Z10,Methodology!$A$2:$A$20,0)),0)) | AD10: =AC10*MC_day_rate
A11: WT-007 | B11: Open | C11: Erosion & sediment control overrun | D11: Shared | E11: Civil & Earthworks | F11: Environmental | G11: Yes | H11: Triangular | I11: CG01 | K11: synthetic cause | L11: synthetic consequence | M11: synthetic controls | N11: Yes | O11: 0.4 | P11: 30000 | Q11: 90000 | R11: 220000 | S11: Wind Farm Beta capex basis | T11: No | U11: 0 | V11: 0 | W11: 0 | X11: 0 | Y11: Synthetic | AA11: per_occurrence | AB11: =IF(O11="","",O11*IF(OR(LOWER(H11)="pert",LOWER(H11)="binary/pert"),(P11+4*Q11+R11)/6,IF(LOWER(H11)="binary",Q11,IF(LOWER(H11)="lognormal",IF(Q11<=0,0,IF(OR(R11<=P11,R11<=0,P11<=0),ABS(Q11),Q11*EXP((MAX((LN(R11)-LN(P11))/(2*1.2816),0.01)^2)/2))),(P11+Q11+R11)/3)))) | AC11: =IF(OR(T11<>"Yes",U11=""),0,U11*(V11+4*W11+X11)/6*IFERROR(INDEX(Methodology!$B$2:$B$20,MATCH(Z11,Methodology!$A$2:$A$20,0)),0)) | AD11: =AC11*MC_day_rate
A12: WT-008 | B12: Open | C12: WTG delivery delay (long-lead) | D12: Wind Farm Owner | E12: Turbine Supply & Erection | F12: Procurement | G12: Yes | H12: PERT | I12: CG02 | K12: synthetic cause | L12: synthetic consequence | M12: synthetic controls | N12: Yes | O12: 0.4 | P12: 200000 | Q12: 600000 | R12: 1500000 | S12: Wind Farm Beta capex basis | T12: Yes | U12: 0.4 | V12: 8 | W12: 20 | X12: 45 | Y12: Synthetic | Z12: Series | AA12: per_occurrence | AB12: =IF(O12="","",O12*IF(OR(LOWER(H12)="pert",LOWER(H12)="binary/pert"),(P12+4*Q12+R12)/6,IF(LOWER(H12)="binary",Q12,IF(LOWER(H12)="lognormal",IF(Q12<=0,0,IF(OR(R12<=P12,R12<=0,P12<=0),ABS(Q12),Q12*EXP((MAX((LN(R12)-LN(P12))/(2*1.2816),0.01)^2)/2))),(P12+Q12+R12)/3)))) | AC12: =IF(OR(T12<>"Yes",U12=""),0,U12*(V12+4*W12+X12)/6*IFERROR(INDEX(Methodology!$B$2:$B$20,MATCH(Z12,Methodology!$A$2:$A$20,0)),0)) | AD12: =AC12*MC_day_rate
A13: WT-009 | B13: Open | C13: Main crane mobilisation delay | D13: EPC Contractor | E13: Turbine Supply & Erection | F13: Heavy Lift | G13: Yes | H13: Triangular | I13: CG02 | K13: synthetic cause | L13: synthetic consequence | M13: synthetic controls | N13: Yes | O13: 0.45 | P13: 150000 | Q13: 450000 | R13: 1200000 | S13: Wind Farm Beta capex basis | T13: Yes | U13: 0.45 | V13: 4 | W13: 10 | X13: 24 | Y13: Synthetic | Z13: Hybrid | AA13: per_occurrence | AB13: =IF(O13="","",O13*IF(OR(LOWER(H13)="pert",LOWER(H13)="binary/pert"),(P13+4*Q13+R13)/6,IF(LOWER(H13)="binary",Q13,IF(LOWER(H13)="lognormal",IF(Q13<=0,0,IF(OR(R13<=P13,R13<=0,P13<=0),ABS(Q13),Q13*EXP((MAX((LN(R13)-LN(P13))/(2*1.2816),0.01)^2)/2))),(P13+Q13+R13)/3)))) | AC13: =IF(OR(T13<>"Yes",U13=""),0,U13*(V13+4*W13+X13)/6*IFERROR(INDEX(Methodology!$B$2:$B$20,MATCH(Z13,Methodology!$A$2:$A$20,0)),0)) | AD13: =AC13*MC_day_rate
A14: WT-010 | B14: Open | C14: Blade transport damage | D14: EPC Contractor | E14: Turbine Supply & Erection | F14: Logistics | G14: Yes | H14: PERT | I14: CG02 | K14: synthetic cause | L14: synthetic consequence | M14: synthetic controls | N14: Yes | O14: 0.3 | P14: 120000 | Q14: 350000 | R14: 900000 | S14: Wind Farm Beta capex basis | T14: No | U14: 0 | V14: 0 | W14: 0 | X14: 0 | Y14: Synthetic | AA14: per_occurrence | AB14: =IF(O14="","",O14*IF(OR(LOWER(H14)="pert",LOWER(H14)="binary/pert"),(P14+4*Q14+R14)/6,IF(LOWER(H14)="binary",Q14,IF(LOWER(H14)="lognormal",IF(Q14<=0,0,IF(OR(R14<=P14,R14<=0,P14<=0),ABS(Q14),Q14*EXP((MAX((LN(R14)-LN(P14))/(2*1.2816),0.01)^2)/2))),(P14+Q14+R14)/3)))) | AC14: =IF(OR(T14<>"Yes",U14=""),0,U14*(V14+4*W14+X14)/6*IFERROR(INDEX(Methodology!$B$2:$B$20,MATCH(Z14,Methodology!$A$2:$A$20,0)),0)) | AD14: =AC14*MC_day_rate
A15: WT-011 | B15: Open | C15: Tower section nonconformance | D15: Wind Farm Owner | E15: Turbine Supply & Erection | F15: Quality | G15: Yes | H15: Lognormal | I15: CG02 | K15: synthetic cause | L15: synthetic consequence | M15: synthetic controls | N15: Yes | O15: 0.25 | P15: 200000 | Q15: 500000 | R15: 1400000 | S15: Wind Farm Beta capex basis | T15: No | U15: 0 | V15: 0 | W15: 0 | X15: 0 | Y15: Synthetic | AA15: per_occurrence | AB15: =IF(O15="","",O15*IF(OR(LOWER(H15)="pert",LOWER(H15)="binary/pert"),(P15+4*Q15+R15)/6,IF(LOWER(H15)="binary",Q15,IF(LOWER(H15)="lognormal",IF(Q15<=0,0,IF(OR(R15<=P15,R15<=0,P15<=0),ABS(Q15),Q15*EXP((MAX((LN(R15)-LN(P15))/(2*1.2816),0.01)^2)/2))),(P15+Q15+R15)/3)))) | AC15: =IF(OR(T15<>"Yes",U15=""),0,U15*(V15+4*W15+X15)/6*IFERROR(INDEX(Methodology!$B$2:$B$20,MATCH(Z15,Methodology!$A$2:$A$20,0)),0)) | AD15: =AC15*MC_day_rate
A16: WT-012 | B16: Open | C16: Erection weather standby | D16: EPC Contractor | E16: Turbine Supply & Erection | F16: Weather | G16: Yes | H16: Triangular | I16: CG02 | K16: synthetic cause | L16: synthetic consequence | M16: synthetic controls | N16: Yes | O16: 0.6 | P16: 100000 | Q16: 300000 | R16: 800000 | S16: Wind Farm Beta capex basis | T16: No | U16: 0 | V16: 0 | W16: 0 | X16: 0 | Y16: Synthetic | AA16: per_occurrence | AB16: =IF(O16="","",O16*IF(OR(LOWER(H16)="pert",LOWER(H16)="binary/pert"),(P16+4*Q16+R16)/6,IF(LOWER(H16)="binary",Q16,IF(LOWER(H16)="lognormal",IF(Q16<=0,0,IF(OR(R16<=P16,R16<=0,P16<=0),ABS(Q16),Q16*EXP((MAX((LN(R16)-LN(P16))/(2*1.2816),0.01)^2)/2))),(P16+Q16+R16)/3)))) | AC16: =IF(OR(T16<>"Yes",U16=""),0,U16*(V16+4*W16+X16)/6*IFERROR(INDEX(Methodology!$B$2:$B$20,MATCH(Z16,Methodology!$A$2:$A$20,0)),0)) | AD16: =AC16*MC_day_rate
A17: WT-013 | B17: Open | C17: Bolt tensioning / torque rework | D17: EPC Contractor | E17: Turbine Supply & Erection | F17: Mechanical | G17: Yes | H17: PERT | I17: CG02 | K17: synthetic cause | L17: synthetic consequence | M17: synthetic controls | N17: Yes | O17: 0.35 | P17: 60000 | Q17: 180000 | R17: 450000 | S17: Wind Farm Beta capex basis | T17: No | U17: 0 | V17: 0 | W17: 0 | X17: 0 | Y17: Synthetic | AA17: per_occurrence | AB17: =IF(O17="","",O17*IF(OR(LOWER(H17)="pert",LOWER(H17)="binary/pert"),(P17+4*Q17+R17)/6,IF(LOWER(H17)="binary",Q17,IF(LOWER(H17)="lognormal",IF(Q17<=0,0,IF(OR(R17<=P17,R17<=0,P17<=0),ABS(Q17),Q17*EXP((MAX((LN(R17)-LN(P17))/(2*1.2816),0.01)^2)/2))),(P17+Q17+R17)/3)))) | AC17: =IF(OR(T17<>"Yes",U17=""),0,U17*(V17+4*W17+X17)/6*IFERROR(INDEX(Methodology!$B$2:$B$20,MATCH(Z17,Methodology!$A$2:$A$20,0)),0)) | AD17: =AC17*MC_day_rate
A18: WT-014 | B18: Open | C18: Major component warranty defect | D18: Wind Farm Owner | E18: Turbine Supply & Erection | F18: Warranty | G18: Yes | H18: PERT | I18: CG02 | K18: synthetic cause | L18: synthetic consequence | M18: synthetic controls | N18: Yes | O18: 0.2 | P18: 250000 | Q18: 700000 | R18: 2000000 | S18: Wind Farm Beta capex basis | T18: No | U18: 0 | V18: 0 | W18: 0 | X18: 0 | Y18: Synthetic | AA18: per_occurrence | AB18: =IF(O18="","",O18*IF(OR(LOWER(H18)="pert",LOWER(H18)="binary/pert"),(P18+4*Q18+R18)/6,IF(LOWER(H18)="binary",Q18,IF(LOWER(H18)="lognormal",IF(Q18<=0,0,IF(OR(R18<=P18,R18<=0,P18<=0),ABS(Q18),Q18*EXP((MAX((LN(R18)-LN(P18))/(2*1.2816),0.01)^2)/2))),(P18+Q18+R18)/3)))) | AC18: =IF(OR(T18<>"Yes",U18=""),0,U18*(V18+4*W18+X18)/6*IFERROR(INDEX(Methodology!$B$2:$B$20,MATCH(Z18,Methodology!$A$2:$A$20,0)),0)) | AD18: =AC18*MC_day_rate
A19: WT-015 | B19: Open | C19: Gearbox / main-bearing replacement | D19: Wind Farm Owner | E19: Turbine Supply & Erection | F19: Mechanical | G19: Yes | H19: Lognormal | I19: CG02 | K19: synthetic cause | L19: synthetic consequence | M19: synthetic controls | N19: Yes | O19: 0.15 | P19: 300000 | Q19: 800000 | R19: 2400000 | S19: Wind Farm Beta capex basis | T19: No | U19: 0 | V19: 0 | W19: 0 | X19: 0 | Y19: Synthetic | AA19: per_occurrence | AB19: =IF(O19="","",O19*IF(OR(LOWER(H19)="pert",LOWER(H19)="binary/pert"),(P19+4*Q19+R19)/6,IF(LOWER(H19)="binary",Q19,IF(LOWER(H19)="lognormal",IF(Q19<=0,0,IF(OR(R19<=P19,R19<=0,P19<=0),ABS(Q19),Q19*EXP((MAX((LN(R19)-LN(P19))/(2*1.2816),0.01)^2)/2))),(P19+Q19+R19)/3)))) | AC19: =IF(OR(T19<>"Yes",U19=""),0,U19*(V19+4*W19+X19)/6*IFERROR(INDEX(Methodology!$B$2:$B$20,MATCH(Z19,Methodology!$A$2:$A$20,0)),0)) | AD19: =AC19*MC_day_rate
A20: WT-016 | B20: Open | C20: Array cable supply shortfall | D20: EPC Contractor | E20: Electrical Reticulation | F20: Procurement | G20: Yes | H20: PERT | I20: CG03 | K20: synthetic cause | L20: synthetic consequence | M20: synthetic controls | N20: Yes | O20: 0.45 | P20: 90000 | Q20: 250000 | R20: 600000 | S20: Wind Farm Beta capex basis | T20: No | U20: 0 | V20: 0 | W20: 0 | X20: 0 | Y20: Synthetic | AA20: per_occurrence | AB20: =IF(O20="","",O20*IF(OR(LOWER(H20)="pert",LOWER(H20)="binary/pert"),(P20+4*Q20+R20)/6,IF(LOWER(H20)="binary",Q20,IF(LOWER(H20)="lognormal",IF(Q20<=0,0,IF(OR(R20<=P20,R20<=0,P20<=0),ABS(Q20),Q20*EXP((MAX((LN(R20)-LN(P20))/(2*1.2816),0.01)^2)/2))),(P20+Q20+R20)/3)))) | AC20: =IF(OR(T20<>"Yes",U20=""),0,U20*(V20+4*W20+X20)/6*IFERROR(INDEX(Methodology!$B$2:$B$20,MATCH(Z20,Methodology!$A$2:$A$20,0)),0)) | AD20: =AC20*MC_day_rate
A21: WT-017 | B21: Open | C21: Cable installation productivity | D21: EPC Contractor | E21: Electrical Reticulation | F21: Construction | G21: Yes | H21: PERT | I21: CG03 | K21: synthetic cause | L21: synthetic consequence | M21: synthetic controls | N21: Yes | O21: 0.4 | P21: 70000 | Q21: 220000 | R21: 520000 | S21: Wind Farm Beta capex basis | T21: No | U21: 0 | V21: 0 | W21: 0 | X21: 0 | Y21: Synthetic | AA21: per_occurrence | AB21: =IF(O21="","",O21*IF(OR(LOWER(H21)="pert",LOWER(H21)="binary/pert"),(P21+4*Q21+R21)/6,IF(LOWER(H21)="binary",Q21,IF(LOWER(H21)="lognormal",IF(Q21<=0,0,IF(OR(R21<=P21,R21<=0,P21<=0),ABS(Q21),Q21*EXP((MAX((LN(R21)-LN(P21))/(2*1.2816),0.01)^2)/2))),(P21+Q21+R21)/3)))) | AC21: =IF(OR(T21<>"Yes",U21=""),0,U21*(V21+4*W21+X21)/6*IFERROR(INDEX(Methodology!$B$2:$B$20,MATCH(Z21,Methodology!$A$2:$A$20,0)),0)) | AD21: =AC21*MC_day_rate
A22: WT-018 | B22: Open | C22: Cable joint re-termination | D22: EPC Contractor | E22: Electrical Reticulation | F22: Electrical | G22: Yes | H22: Triangular | I22: CG03 | K22: synthetic cause | L22: synthetic consequence | M22: synthetic controls | N22: Yes | O22: 0.3 | P22: 50000 | Q22: 150000 | R22: 400000 | S22: Wind Farm Beta capex basis | T22: No | U22: 0 | V22: 0 | W22: 0 | X22: 0 | Y22: Synthetic | AA22: per_occurrence | AB22: =IF(O22="","",O22*IF(OR(LOWER(H22)="pert",LOWER(H22)="binary/pert"),(P22+4*Q22+R22)/6,IF(LOWER(H22)="binary",Q22,IF(LOWER(H22)="lognormal",IF(Q22<=0,0,IF(OR(R22<=P22,R22<=0,P22<=0),ABS(Q22),Q22*EXP((MAX((LN(R22)-LN(P22))/(2*1.2816),0.01)^2)/2))),(P22+Q22+R22)/3)))) | AC22: =IF(OR(T22<>"Yes",U22=""),0,U22*(V22+4*W22+X22)/6*IFERROR(INDEX(Methodology!$B$2:$B$20,MATCH(Z22,Methodology!$A$2:$A$20,0)),0)) | AD22: =AC22*MC_day_rate
A23: WT-019 | B23: Open | C23: Trenching clash with civil works | D23: Shared | E23: Electrical Reticulation | F23: Interface | G23: Yes | H23: PERT | I23: CG03 | K23: synthetic cause | L23: synthetic consequence | M23: synthetic controls | N23: Yes | O23: 0.25 | P23: 40000 | Q23: 120000 | R23: 300000 | S23: Wind Farm Beta capex basis | T23: No | U23: 0 | V23: 0 | W23: 0 | X23: 0 | Y23: Synthetic | AA23: per_occurrence | AB23: =IF(O23="","",O23*IF(OR(LOWER(H23)="pert",LOWER(H23)="binary/pert"),(P23+4*Q23+R23)/6,IF(LOWER(H23)="binary",Q23,IF(LOWER(H23)="lognormal",IF(Q23<=0,0,IF(OR(R23<=P23,R23<=0,P23<=0),ABS(Q23),Q23*EXP((MAX((LN(R23)-LN(P23))/(2*1.2816),0.01)^2)/2))),(P23+Q23+R23)/3)))) | AC23: =IF(OR(T23<>"Yes",U23=""),0,U23*(V23+4*W23+X23)/6*IFERROR(INDEX(Methodology!$B$2:$B$20,MATCH(Z23,Methodology!$A$2:$A$20,0)),0)) | AD23: =AC23*MC_day_rate
A24: WT-020 | B24: Open | C24: HV array cable test failures | D24: EPC Contractor | E24: Electrical Reticulation | F24: Testing | G24: Yes | H24: Triangular | I24: CG03 | K24: synthetic cause | L24: synthetic consequence | M24: synthetic controls | N24: Yes | O24: 0.35 | P24: 60000 | Q24: 170000 | R24: 420000 | S24: Wind Farm Beta capex basis | T24: Yes | U24: 0.35 | V24: 1 | W24: 4 | X24: 10 | Y24: Synthetic | Z24: Parallel | AA24: per_occurrence | AB24: =IF(O24="","",O24*IF(OR(LOWER(H24)="pert",LOWER(H24)="binary/pert"),(P24+4*Q24+R24)/6,IF(LOWER(H24)="binary",Q24,IF(LOWER(H24)="lognormal",IF(Q24<=0,0,IF(OR(R24<=P24,R24<=0,P24<=0),ABS(Q24),Q24*EXP((MAX((LN(R24)-LN(P24))/(2*1.2816),0.01)^2)/2))),(P24+Q24+R24)/3)))) | AC24: =IF(OR(T24<>"Yes",U24=""),0,U24*(V24+4*W24+X24)/6*IFERROR(INDEX(Methodology!$B$2:$B$20,MATCH(Z24,Methodology!$A$2:$A$20,0)),0)) | AD24: =AC24*MC_day_rate
A25: WT-021 | B25: Open | C25: Grid connection redesign | D25: Wind Farm Owner | E25: Grid Connection | F25: Design | G25: Yes | H25: Lognormal | I25: CG04 | K25: synthetic cause | L25: synthetic consequence | M25: synthetic controls | N25: Yes | O25: 0.3 | P25: 200000 | Q25: 500000 | R25: 1200000 | S25: Wind Farm Beta capex basis | T25: Yes | U25: 0.3 | V25: 6 | W25: 15 | X25: 35 | Y25: Synthetic | Z25: Series | AA25: per_occurrence | AB25: =IF(O25="","",O25*IF(OR(LOWER(H25)="pert",LOWER(H25)="binary/pert"),(P25+4*Q25+R25)/6,IF(LOWER(H25)="binary",Q25,IF(LOWER(H25)="lognormal",IF(Q25<=0,0,IF(OR(R25<=P25,R25<=0,P25<=0),ABS(Q25),Q25*EXP((MAX((LN(R25)-LN(P25))/(2*1.2816),0.01)^2)/2))),(P25+Q25+R25)/3)))) | AC25: =IF(OR(T25<>"Yes",U25=""),0,U25*(V25+4*W25+X25)/6*IFERROR(INDEX(Methodology!$B$2:$B$20,MATCH(Z25,Methodology!$A$2:$A$20,0)),0)) | AD25: =AC25*MC_day_rate
A26: WT-022 | B26: Open | C26: Network operator approval delay | D26: Wind Farm Owner | E26: Grid Connection | F26: Approvals | G26: Yes | H26: PERT | I26: CG04 | K26: synthetic cause | L26: synthetic consequence | M26: synthetic controls | N26: Yes | O26: 0.4 | P26: 100000 | Q26: 280000 | R26: 700000 | S26: Wind Farm Beta capex basis | T26: No | U26: 0 | V26: 0 | W26: 0 | X26: 0 | Y26: Synthetic | AA26: per_occurrence | AB26: =IF(O26="","",O26*IF(OR(LOWER(H26)="pert",LOWER(H26)="binary/pert"),(P26+4*Q26+R26)/6,IF(LOWER(H26)="binary",Q26,IF(LOWER(H26)="lognormal",IF(Q26<=0,0,IF(OR(R26<=P26,R26<=0,P26<=0),ABS(Q26),Q26*EXP((MAX((LN(R26)-LN(P26))/(2*1.2816),0.01)^2)/2))),(P26+Q26+R26)/3)))) | AC26: =IF(OR(T26<>"Yes",U26=""),0,U26*(V26+4*W26+X26)/6*IFERROR(INDEX(Methodology!$B$2:$B$20,MATCH(Z26,Methodology!$A$2:$A$20,0)),0)) | AD26: =AC26*MC_day_rate
A27: WT-023 | B27: Open | C27: Protection settings rework | D27: Shared | E27: Grid Connection | F27: Electrical | G27: Yes | H27: Triangular | I27: CG04 | K27: synthetic cause | L27: synthetic consequence | M27: synthetic controls | N27: Yes | O27: 0.3 | P27: 60000 | Q27: 160000 | R27: 380000 | S27: Wind Farm Beta capex basis | T27: No | U27: 0 | V27: 0 | W27: 0 | X27: 0 | Y27: Synthetic | AA27: per_occurrence | AB27: =IF(O27="","",O27*IF(OR(LOWER(H27)="pert",LOWER(H27)="binary/pert"),(P27+4*Q27+R27)/6,IF(LOWER(H27)="binary",Q27,IF(LOWER(H27)="lognormal",IF(Q27<=0,0,IF(OR(R27<=P27,R27<=0,P27<=0),ABS(Q27),Q27*EXP((MAX((LN(R27)-LN(P27))/(2*1.2816),0.01)^2)/2))),(P27+Q27+R27)/3)))) | AC27: =IF(OR(T27<>"Yes",U27=""),0,U27*(V27+4*W27+X27)/6*IFERROR(INDEX(Methodology!$B$2:$B$20,MATCH(Z27,Methodology!$A$2:$A$20,0)),0)) | AD27: =AC27*MC_day_rate
A28: WT-024 | B28: Open | C28: Grid compliance test failure | D28: Wind Farm Owner | E28: Grid Connection | F28: Testing | G28: Yes | H28: PERT | I28: CG04 | K28: synthetic cause | L28: synthetic consequence | M28: synthetic controls | N28: Yes | O28: 0.25 | P28: 120000 | Q28: 320000 | R28: 800000 | S28: Wind Farm Beta capex basis | T28: No | U28: 0 | V28: 0 | W28: 0 | X28: 0 | Y28: Synthetic | AA28: per_occurrence | AB28: =IF(O28="","",O28*IF(OR(LOWER(H28)="pert",LOWER(H28)="binary/pert"),(P28+4*Q28+R28)/6,IF(LOWER(H28)="binary",Q28,IF(LOWER(H28)="lognormal",IF(Q28<=0,0,IF(OR(R28<=P28,R28<=0,P28<=0),ABS(Q28),Q28*EXP((MAX((LN(R28)-LN(P28))/(2*1.2816),0.01)^2)/2))),(P28+Q28+R28)/3)))) | AC28: =IF(OR(T28<>"Yes",U28=""),0,U28*(V28+4*W28+X28)/6*IFERROR(INDEX(Methodology!$B$2:$B$20,MATCH(Z28,Methodology!$A$2:$A$20,0)),0)) | AD28: =AC28*MC_day_rate
A29: WT-025 | B29: Open | C29: Connection-point scope change | D29: Wind Farm Owner | E29: Grid Connection | F29: Scope | G29: Yes | H29: Triangular | I29: CG04 | K29: synthetic cause | L29: synthetic consequence | M29: synthetic controls | N29: Yes | O29: 0.2 | P29: 80000 | Q29: 200000 | R29: 500000 | S29: Wind Farm Beta capex basis | T29: No | U29: 0 | V29: 0 | W29: 0 | X29: 0 | Y29: Synthetic | AA29: per_occurrence | AB29: =IF(O29="","",O29*IF(OR(LOWER(H29)="pert",LOWER(H29)="binary/pert"),(P29+4*Q29+R29)/6,IF(LOWER(H29)="binary",Q29,IF(LOWER(H29)="lognormal",IF(Q29<=0,0,IF(OR(R29<=P29,R29<=0,P29<=0),ABS(Q29),Q29*EXP((MAX((LN(R29)-LN(P29))/(2*1.2816),0.01)^2)/2))),(P29+Q29+R29)/3)))) | AC29: =IF(OR(T29<>"Yes",U29=""),0,U29*(V29+4*W29+X29)/6*IFERROR(INDEX(Methodology!$B$2:$B$20,MATCH(Z29,Methodology!$A$2:$A$20,0)),0)) | AD29: =AC29*MC_day_rate
A30: WT-026 | B30: Open | C30: Substation civils delay | D30: EPC Contractor | E30: Balance of Plant | F30: Civil | G30: Yes | H30: PERT | I30: CG05 | K30: synthetic cause | L30: synthetic consequence | M30: synthetic controls | N30: Yes | O30: 0.35 | P30: 80000 | Q30: 220000 | R30: 550000 | S30: Wind Farm Beta capex basis | T30: Yes | U30: 0.35 | V30: 2 | W30: 6 | X30: 14 | Y30: Synthetic | Z30: Hybrid | AA30: per_occurrence | AB30: =IF(O30="","",O30*IF(OR(LOWER(H30)="pert",LOWER(H30)="binary/pert"),(P30+4*Q30+R30)/6,IF(LOWER(H30)="binary",Q30,IF(LOWER(H30)="lognormal",IF(Q30<=0,0,IF(OR(R30<=P30,R30<=0,P30<=0),ABS(Q30),Q30*EXP((MAX((LN(R30)-LN(P30))/(2*1.2816),0.01)^2)/2))),(P30+Q30+R30)/3)))) | AC30: =IF(OR(T30<>"Yes",U30=""),0,U30*(V30+4*W30+X30)/6*IFERROR(INDEX(Methodology!$B$2:$B$20,MATCH(Z30,Methodology!$A$2:$A$20,0)),0)) | AD30: =AC30*MC_day_rate
A31: WT-027 | B31: Open | C31: Substation E&I commissioning slip | D31: Shared | E31: Balance of Plant | F31: Commissioning | G31: Yes | H31: Triangular | I31: CG05 | K31: synthetic cause | L31: synthetic consequence | M31: synthetic controls | N31: Yes | O31: 0.35 | P31: 60000 | Q31: 180000 | R31: 450000 | S31: Wind Farm Beta capex basis | T31: Yes | U31: 0.35 | V31: 1 | W31: 4 | X31: 10 | Y31: Synthetic | Z31: Parallel | AA31: per_occurrence | AB31: =IF(O31="","",O31*IF(OR(LOWER(H31)="pert",LOWER(H31)="binary/pert"),(P31+4*Q31+R31)/6,IF(LOWER(H31)="binary",Q31,IF(LOWER(H31)="lognormal",IF(Q31<=0,0,IF(OR(R31<=P31,R31<=0,P31<=0),ABS(Q31),Q31*EXP((MAX((LN(R31)-LN(P31))/(2*1.2816),0.01)^2)/2))),(P31+Q31+R31)/3)))) | AC31: =IF(OR(T31<>"Yes",U31=""),0,U31*(V31+4*W31+X31)/6*IFERROR(INDEX(Methodology!$B$2:$B$20,MATCH(Z31,Methodology!$A$2:$A$20,0)),0)) | AD31: =AC31*MC_day_rate
A32: WT-028 | B32: Open | C32: Power transformer delivery delay | D32: Wind Farm Owner | E32: Balance of Plant | F32: Procurement | G32: Yes | H32: PERT | I32: CG05 | K32: synthetic cause | L32: synthetic consequence | M32: synthetic controls | N32: Yes | O32: 0.25 | P32: 150000 | Q32: 400000 | R32: 1000000 | S32: Wind Farm Beta capex basis | T32: No | U32: 0 | V32: 0 | W32: 0 | X32: 0 | Y32: Synthetic | AA32: per_occurrence | AB32: =IF(O32="","",O32*IF(OR(LOWER(H32)="pert",LOWER(H32)="binary/pert"),(P32+4*Q32+R32)/6,IF(LOWER(H32)="binary",Q32,IF(LOWER(H32)="lognormal",IF(Q32<=0,0,IF(OR(R32<=P32,R32<=0,P32<=0),ABS(Q32),Q32*EXP((MAX((LN(R32)-LN(P32))/(2*1.2816),0.01)^2)/2))),(P32+Q32+R32)/3)))) | AC32: =IF(OR(T32<>"Yes",U32=""),0,U32*(V32+4*W32+X32)/6*IFERROR(INDEX(Methodology!$B$2:$B$20,MATCH(Z32,Methodology!$A$2:$A$20,0)),0)) | AD32: =AC32*MC_day_rate
A33: WT-029 | B33: Open | C33: Control building fit-out overrun | D33: EPC Contractor | E33: Balance of Plant | F33: Building | G33: Yes | H33: Triangular | I33: CG05 | K33: synthetic cause | L33: synthetic consequence | M33: synthetic controls | N33: Yes | O33: 0.3 | P33: 50000 | Q33: 140000 | R33: 320000 | S33: Wind Farm Beta capex basis | T33: No | U33: 0 | V33: 0 | W33: 0 | X33: 0 | Y33: Synthetic | AA33: per_occurrence | AB33: =IF(O33="","",O33*IF(OR(LOWER(H33)="pert",LOWER(H33)="binary/pert"),(P33+4*Q33+R33)/6,IF(LOWER(H33)="binary",Q33,IF(LOWER(H33)="lognormal",IF(Q33<=0,0,IF(OR(R33<=P33,R33<=0,P33<=0),ABS(Q33),Q33*EXP((MAX((LN(R33)-LN(P33))/(2*1.2816),0.01)^2)/2))),(P33+Q33+R33)/3)))) | AC33: =IF(OR(T33<>"Yes",U33=""),0,U33*(V33+4*W33+X33)/6*IFERROR(INDEX(Methodology!$B$2:$B$20,MATCH(Z33,Methodology!$A$2:$A$20,0)),0)) | AD33: =AC33*MC_day_rate
A34: WT-030 | B34: Open | C34: Earthing & lightning protection rework | D34: EPC Contractor | E34: Balance of Plant | F34: Electrical | G34: Yes | H34: PERT | I34: CG05 | K34: synthetic cause | L34: synthetic consequence | M34: synthetic controls | N34: Yes | O34: 0.25 | P34: 40000 | Q34: 110000 | R34: 280000 | S34: Wind Farm Beta capex basis | T34: No | U34: 0 | V34: 0 | W34: 0 | X34: 0 | Y34: Synthetic | AA34: per_occurrence | AB34: =IF(O34="","",O34*IF(OR(LOWER(H34)="pert",LOWER(H34)="binary/pert"),(P34+4*Q34+R34)/6,IF(LOWER(H34)="binary",Q34,IF(LOWER(H34)="lognormal",IF(Q34<=0,0,IF(OR(R34<=P34,R34<=0,P34<=0),ABS(Q34),Q34*EXP((MAX((LN(R34)-LN(P34))/(2*1.2816),0.01)^2)/2))),(P34+Q34+R34)/3)))) | AC34: =IF(OR(T34<>"Yes",U34=""),0,U34*(V34+4*W34+X34)/6*IFERROR(INDEX(Methodology!$B$2:$B$20,MATCH(Z34,Methodology!$A$2:$A$20,0)),0)) | AD34: =AC34*MC_day_rate
A35: WT-031 | B35: Open | C35: SCADA integration defects | D35: Shared | E35: Commissioning & Controls | F35: Controls | G35: Yes | H35: PERT | I35: CG06 | K35: synthetic cause | L35: synthetic consequence | M35: synthetic controls | N35: Yes | O35: 0.5 | P35: 110000 | Q35: 300000 | R35: 700000 | S35: Wind Farm Beta capex basis | T35: Yes | U35: 0.5 | V35: 4 | W35: 9 | X35: 19 | Y35: Synthetic | Z35: Series | AA35: per_occurrence | AB35: =IF(O35="","",O35*IF(OR(LOWER(H35)="pert",LOWER(H35)="binary/pert"),(P35+4*Q35+R35)/6,IF(LOWER(H35)="binary",Q35,IF(LOWER(H35)="lognormal",IF(Q35<=0,0,IF(OR(R35<=P35,R35<=0,P35<=0),ABS(Q35),Q35*EXP((MAX((LN(R35)-LN(P35))/(2*1.2816),0.01)^2)/2))),(P35+Q35+R35)/3)))) | AC35: =IF(OR(T35<>"Yes",U35=""),0,U35*(V35+4*W35+X35)/6*IFERROR(INDEX(Methodology!$B$2:$B$20,MATCH(Z35,Methodology!$A$2:$A$20,0)),0)) | AD35: =AC35*MC_day_rate
A36: WT-032 | B36: Open | C36: Turbine commissioning faults | D36: EPC Contractor | E36: Commissioning & Controls | F36: Commissioning | G36: Yes | H36: Triangular | I36: CG06 | K36: synthetic cause | L36: synthetic consequence | M36: synthetic controls | N36: Yes | O36: 0.45 | P36: 90000 | Q36: 250000 | R36: 600000 | S36: Wind Farm Beta capex basis | T36: Yes | U36: 0.45 | V36: 3 | W36: 7 | X36: 16 | Y36: Synthetic | Z36: Hybrid | AA36: per_occurrence | AB36: =IF(O36="","",O36*IF(OR(LOWER(H36)="pert",LOWER(H36)="binary/pert"),(P36+4*Q36+R36)/6,IF(LOWER(H36)="binary",Q36,IF(LOWER(H36)="lognormal",IF(Q36<=0,0,IF(OR(R36<=P36,R36<=0,P36<=0),ABS(Q36),Q36*EXP((MAX((LN(R36)-LN(P36))/(2*1.2816),0.01)^2)/2))),(P36+Q36+R36)/3)))) | AC36: =IF(OR(T36<>"Yes",U36=""),0,U36*(V36+4*W36+X36)/6*IFERROR(INDEX(Methodology!$B$2:$B$20,MATCH(Z36,Methodology!$A$2:$A$20,0)),0)) | AD36: =AC36*MC_day_rate
A37: WT-033 | B37: Open | C37: Power performance test shortfall | D37: Wind Farm Owner | E37: Commissioning & Controls | F37: Testing | G37: Yes | H37: PERT | I37: CG06 | K37: synthetic cause | L37: synthetic consequence | M37: synthetic controls | N37: Yes | O37: 0.3 | P37: 60000 | Q37: 160000 | R37: 400000 | S37: Wind Farm Beta capex basis | T37: No | U37: 0 | V37: 0 | W37: 0 | X37: 0 | Y37: Synthetic | AA37: per_occurrence | AB37: =IF(O37="","",O37*IF(OR(LOWER(H37)="pert",LOWER(H37)="binary/pert"),(P37+4*Q37+R37)/6,IF(LOWER(H37)="binary",Q37,IF(LOWER(H37)="lognormal",IF(Q37<=0,0,IF(OR(R37<=P37,R37<=0,P37<=0),ABS(Q37),Q37*EXP((MAX((LN(R37)-LN(P37))/(2*1.2816),0.01)^2)/2))),(P37+Q37+R37)/3)))) | AC37: =IF(OR(T37<>"Yes",U37=""),0,U37*(V37+4*W37+X37)/6*IFERROR(INDEX(Methodology!$B$2:$B$20,MATCH(Z37,Methodology!$A$2:$A$20,0)),0)) | AD37: =AC37*MC_day_rate
A38: WT-034 | B38: Open | C38: Grid code compliance retest | D38: Shared | E38: Commissioning & Controls | F38: Testing | G38: Yes | H38: Triangular | I38: CG06 | K38: synthetic cause | L38: synthetic consequence | M38: synthetic controls | N38: Yes | O38: 0.25 | P38: 70000 | Q38: 180000 | R38: 450000 | S38: Wind Farm Beta capex basis | T38: No | U38: 0 | V38: 0 | W38: 0 | X38: 0 | Y38: Synthetic | AA38: per_occurrence | AB38: =IF(O38="","",O38*IF(OR(LOWER(H38)="pert",LOWER(H38)="binary/pert"),(P38+4*Q38+R38)/6,IF(LOWER(H38)="binary",Q38,IF(LOWER(H38)="lognormal",IF(Q38<=0,0,IF(OR(R38<=P38,R38<=0,P38<=0),ABS(Q38),Q38*EXP((MAX((LN(R38)-LN(P38))/(2*1.2816),0.01)^2)/2))),(P38+Q38+R38)/3)))) | AC38: =IF(OR(T38<>"Yes",U38=""),0,U38*(V38+4*W38+X38)/6*IFERROR(INDEX(Methodology!$B$2:$B$20,MATCH(Z38,Methodology!$A$2:$A$20,0)),0)) | AD38: =AC38*MC_day_rate
A39: WT-035 | B39: Open | C39: Punchlist / defects liability | D39: EPC Contractor | E39: Commissioning & Controls | F39: Closeout | G39: Yes | H39: PERT | I39: CG06 | K39: synthetic cause | L39: synthetic consequence | M39: synthetic controls | N39: Yes | O39: 0.4 | P39: 50000 | Q39: 140000 | R39: 350000 | S39: Wind Farm Beta capex basis | T39: No | U39: 0 | V39: 0 | W39: 0 | X39: 0 | Y39: Synthetic | AA39: per_occurrence | AB39: =IF(O39="","",O39*IF(OR(LOWER(H39)="pert",LOWER(H39)="binary/pert"),(P39+4*Q39+R39)/6,IF(LOWER(H39)="binary",Q39,IF(LOWER(H39)="lognormal",IF(Q39<=0,0,IF(OR(R39<=P39,R39<=0,P39<=0),ABS(Q39),Q39*EXP((MAX((LN(R39)-LN(P39))/(2*1.2816),0.01)^2)/2))),(P39+Q39+R39)/3)))) | AC39: =IF(OR(T39<>"Yes",U39=""),0,U39*(V39+4*W39+X39)/6*IFERROR(INDEX(Methodology!$B$2:$B$20,MATCH(Z39,Methodology!$A$2:$A$20,0)),0)) | AD39: =AC39*MC_day_rate

Sheet EMV & Mode Analysis
A1: EMV & Mode Analysis - Tropic Ridge Wind Farm
A2: Deterministic Layer-1 expected values (means) from the register EMV columns, NOT Monte-Carlo P-levels. Live formulas; refresh on open.
A4: Layer-1 totals
A5: Total cost EMV ($) | B5: =SUM('Risk Register'!AB5:AB39)
A6: Total schedule EMV ($) | B6: =SUM('Risk Register'!AD5:AD39)
A7: Total Layer-1 EMV ($) | B7: =B5+B6
A8: Risks: Series / Hybrid / Parallel | B8: =COUNTIF('Risk Register'!Z5:Z39,"Series")&" / "&COUNTIF('Risk Register'!Z5:Z39,"Hybrid")&" / "&COUNTIF('Risk Register'!Z5:Z39,"Parallel")
A11: Risk | B11: Cost EMV ($)
A12: ='Risk Register'!A5 | B12: ='Risk Register'!AB5
A13: ='Risk Register'!A6 | B13: ='Risk Register'!AB6
A14: ='Risk Register'!A7 | B14: ='Risk Register'!AB7
A15: ='Risk Register'!A8 | B15: ='Risk Register'!AB8
A16: ='Risk Register'!A9 | B16: ='Risk Register'!AB9
A17: ='Risk Register'!A10 | B17: ='Risk Register'!AB10
A18: ='Risk Register'!A11 | B18: ='Risk Register'!AB11
A19: ='Risk Register'!A12 | B19: ='Risk Register'!AB12
A20: ='Risk Register'!A13 | B20: ='Risk Register'!AB13
A21: ='Risk Register'!A14 | B21: ='Risk Register'!AB14
A22: ='Risk Register'!A15 | B22: ='Risk Register'!AB15
A23: ='Risk Register'!A16 | B23: ='Risk Register'!AB16
... A46: ='Risk Register'!A39 | B46: ='Risk Register'!AB39
A49: Risk | B49: Schedule EMV ($)
A50: ='Risk Register'!A5 | B50: ='Risk Register'!AD5
A51: ='Risk Register'!A6 | B51: ='Risk Register'!AD6
A52: ='Risk Register'!A7 | B52: ='Risk Register'!AD7
A53: ='Risk Register'!A8 | B53: ='Risk Register'!AD8
A54: ='Risk Register'!A9 | B54: ='Risk Register'!AD9
A55: ='Risk Register'!A10 | B55: ='Risk Register'!AD10
A56: ='Risk Register'!A11 | B56: ='Risk Register'!AD11
A57: ='Risk Register'!A12 | B57: ='Risk Register'!AD12
A58: ='Risk Register'!A13 | B58: ='Risk Register'!AD13
A59: ='Risk Register'!A14 | B59: ='Risk Register'!AD14
A60: ='Risk Register'!A15 | B60: ='Risk Register'!AD15
A61: ='Risk Register'!A16 | B61: ='Risk Register'!AD16
... A84: ='Risk Register'!A39 | B84: ='Risk Register'!AD39
A87: Layer | B87: EMV ($)
A88: Cost | B88: =B5
A89: Schedule | B89: =B6

Sheet Simulation
A1: P-level | B1: Cost ($) | D1: Cum. prob | E1: Cost ($) | G1: Corr_flag | I1: P-level | J1: rho=0 | K1: elicited | L1: rho=1 | N1: Contract validation
G3: P80 CI half-width (25k)
G4: P80 CI half-width (%)
G6: Amber cells are written by the model (xlwings) - do not edit.

Sheet Lists
A1: Cascade lists - edit here; the Risk Register dropdowns follow.
A2: Distribution | B2: MCInclude | C2: TimeImpact | D2: Recurrence | E2: Mode | F2: CGCode | G2: RBS_L1 | H2: RBS_L2 | I2: Package | J2: Factor
A3: PERT | B3: Yes | C3: Yes | D3: Single | E3: Series | F3: CG01 | G3: Technical | H3: Design | I3: Civil | J3: Provisions
A4: Triangular | B4: No | C4: No | D4: Recurring | E4: Hybrid | F4: CG02 | G4: Commercial | H4: Construction | I4: Structural | J4: Duration
A5: Lognormal | D5: None | E5: Parallel | F5: CG03 | G5: Management | H5: Procurement | I5: Mechanical | J5: Q_Civils
A6: Binary | F6: CG04 | G6: External | H6: Interface | I6: Electrical | J6: Q_Elec
A7: Binary/PERT | F7: CG05 | G7: Environmental | H7: Approvals | I7: Piping | J7: Q_Grid
F8: CG06 | G8: Delivery | H8: Weather | I8: Instrumentation | J8: R_Turbine
F9: CG07 | H9: Ground Conditions | I9: Commissioning | J9: FX
F10: CG08 | H10: Commissioning | I10: Management | J10: R_Concrete
F11: CG09 | J11: R_Steel
F12: CG10 | J12: R_General
F13: CG11 | J13: R_Plant
F14: CG12 | J14: R_Subcon
F15: CG13 | J15: R_Staff
J16: R_Labour

Sheet Mapping
A1: Risk ID | B1: Pattern_ID | C1: Prefix_List | D1: Activity_Count | E1: Gating_Activity_ID | F1: Injection_Method
A2: WT-001 | B2: P-WT-001 | C2: 20.A | D2: 11 | E2: 20.G.001
A3: WT-002 | B3: P-WT-002 | C3: 10.G.001 | D3: 1 | E3: 10.G.001
A4: WT-008 | B4: P-WT-008 | C4: 30.A | D4: 11 | E4: 30.G.001
A5: WT-009 | B5: P-WT-009 | C5: 30.G.002 | D5: 1 | E5: 30.G.002
A6: WT-020 | B6: P-WT-020 | C6: 40.C | D6: 10 | E6: 40.G.001
A7: WT-021 | B7: P-WT-021 | C7: 50.G.001 | D7: 1 | E7: 50.G.001
A8: WT-026 | B8: P-WT-026 | C8: 50.G.002 | D8: 1 | E8: 50.G.002
A9: WT-027 | B9: P-WT-027 | C9: 50.G.003 | D9: 1 | E9: 50.G.003
A10: WT-031 | B10: P-WT-031 | C10: 60.A | D10: 11 | E10: 60.G.001
A11: WT-032 | B11: P-WT-032 | C11: 60.B | D11: 10 | E11: 60.G.002

Sheet MC_Params
B1: MC_Params (legacy VBA config surface - Settings is the LIVE one)
B2: Iterations (n) | C2: 50000
B3: Random seed - legacy cost MC only (0=random; the deliverable's seed is SR9_SEED) | C3: 42
B4: Stakeholder view | C4: All
B5: Reporting P-Level (pct) | C5: 80
B6: TIC - Total Installed Cost ($) | C6: 50000000
B7: Cascade enabled | C7: 1
B8: Cascade slip rate | C8: 1.5
B9: Cascade slip cap | C9: 3
B10: Cascade cost scale | C10: 0.5
B11: Chain 1 trigger - planning delay (months) | C11: 3
B12: Chain 1 - weather amplification factor | C12: 2.5
B13: Chain 2 trigger - site estab delay (weeks) | C13: 2
B14: Chain 2 - cascade factor | C14: 1.5
B15: day_rate ($/wd) | C15: 35000
B16: programme_seasons | C16: 1
... B31: CG06 capex base ($) | C31: 3000000

Sheet Methodology
A1: CG code / Mode | B1: Coefficient / Multiplier | C1: Description
A2: CG01 | B2: 0.6 | C2: Civil & Earthworks
A3: CG02 | B3: 0.5 | C3: Turbine Supply & Erection
A4: CG03 | B4: 0.5 | C4: Electrical Reticulation
A5: CG04 | B5: 0.4 | C5: Grid Connection
A6: CG05 | B6: 0.5 | C6: Balance of Plant / Substation
A7: CG06 | B7: 0.5 | C7: Commissioning & Controls
A8: CG07 | B8: 0.4
A9: CG08 | B9: 0.4
A10: CG09 | B10: 0.4
A11: CG10 | B11: 0.4
A12: CG11 | B12: 0.5
A13: CG12 | B13: 0.5
A14: CG13 | B14: 0.5
A15: Series | B15: 1
A16: Hybrid | B16: 0.5
A17: Parallel | B17: 0
A18: Cost_Calibration_Tolerance_Dollars | B18: 50000 | C18: Cost cross-check: absolute tolerance ($)
A19: Cost_Calibration_Tolerance_Pct | B19: 0.001 | C19: Cost cross-check: relative tolerance (fraction)
A20: Schedule_Calibration_Tolerance_Days | B20: 1 | C20: Schedule cross-check: absolute tolerance (days)
A21: Schedule_Calibration_Tolerance_Pct | B21: 0.05 | C21: Schedule cross-check: relative tolerance (fraction)
A22: Schedule_Top3_Tie_Tolerance_Pct | B22: 0.02 | C22: Schedule top-3 cross-check: two contributors the arms rank apart are one tie when within this fraction of each other in BOTH arms
A23: Default_Injection_Method | B23: discrete_event_additive_days | C23: Dual-coded risks with no Injection_Method on the Mapping sheet take this

Sheet Settings
A1: Iterations (interactive default) | B1: 25000
A2: Random seed | B2: 42
A3: View (owner | shared-pool) | B3: owner
A4: Risk-ID prefix | B4: WT
A5: Iterations (100k on-demand button) | B5: 100000
A6: Contract version | B6: 1.4
A7: Pyodide runtime pin | B7: 314.0.1
A8: Layer 1 enabled (TRUE/FALSE) | B8: TRUE

Sheet Layer1_Base
A1: WBS Row | B1: Staff | C1: Labour | D1: Plant | E1: Concrete | F1: Steel | G1: General | H1: Subcontract | I1: Provisional
A2: Development & approvals | B2: 1 | C2: 0 | D2: 0 | E2: 0 | F2: 0 | G2: 0.3 | H2: 0.2 | I2: 0
A3: Turbine supply | B3: 0 | C3: 0 | D3: 0 | E3: 0 | F3: 0 | G3: 0.5 | H3: 26.5 | I3: 1
A4: Turbine transport & erection | B4: 0.2 | C4: 0.8 | D4: 1.2 | E4: 0 | F4: 0 | G4: 0 | H4: 0.8 | I4: 0
A5: BOP civils | B5: 0 | C5: 1.3 | D5: 1.2 | E5: 1.8 | F5: 0.7 | G5: 0.6 | H5: 0 | I5: 0.4
A6: Electrical BOP | B6: 0.2 | C6: 0.9 | D6: 0 | E6: 0 | F6: 0 | G6: 1.5 | H6: 0.9 | I6: 0
A7: Substation & grid connection | B7: 0.3 | C7: 0 | D7: 0 | E7: 0 | F7: 0.6 | G7: 1.2 | H7: 2.5 | I7: 0.4
A8: Commissioning | B8: 0.4 | C8: 0 | D8: 0 | E8: 0 | F8: 0 | G8: 0.1 | H8: 0.5 | I8: 0
A9: Owners costs & PM | B9: 1.8 | C9: 0 | D9: 0 | E9: 0 | F9: 0 | G9: 0.2 | H9: 0 | I9: 0
A11: Declared_Total ($M) | B11: 50
A12: Units | B12: $M (read x 1,000,000 -> dollars)

Sheet Layer1_Factors
A1: Factor | B1: Driver | C1: Opt_P10 | D1: ML_mode | E1: P90 | F1: Column_Scope
A2: Provisions | B2: provisions | C2: -0.5 | D2: 0 | E2: 0.3 | F2: Provisional
A3: Duration | B3: duration | C3: -0.05 | D3: 0 | E3: 0.15 | F3: ALL
A4: Q_Civils | B4: civils_quantity | C4: -0.08 | D4: 0 | E4: 0.2 | F4: ALL
A5: Q_Elec | B5: elec_quantity | C5: -0.05 | D5: 0 | E5: 0.15 | F5: ALL
A6: Q_Grid | B6: grid_scope | C6: -0.05 | D6: 0 | E6: 0.25 | F6: ALL
A7: R_Turbine | B7: turbine_price | C7: -0.05 | D7: 0 | E7: 0.12 | F7: ALL
A8: FX | B8: fx | C8: -0.06 | D8: 0 | E8: 0.1 | F8: Subcontract,General
A9: R_Concrete | B9: concrete_rate | C9: -0.05 | D9: 0 | E9: 0.15 | F9: Concrete
A10: R_Steel | B10: steel_rate | C10: -0.08 | D10: 0 | E10: 0.2 | F10: Steel
A11: R_General | B11: general_rate | C11: -0.05 | D11: 0 | E11: 0.12 | F11: General
A12: R_Plant | B12: plant_rate | C12: -0.05 | D12: 0 | E12: 0.12 | F12: Plant
A13: R_Subcon | B13: subcon_rate | C13: -0.04 | D13: 0 | E13: 0.1 | F13: Subcontract
... A15: R_Labour | B15: labour_rate | C15: -0.04 | D15: 0 | E15: 0.12 | F15: Labour

Sheet Layer1_Allocation
A1: Factor | B1: Development & approvals | C1: Turbine supply | D1: Turbine transport & erection | E1: BOP civils | F1: Electrical BOP | G1: Substation & grid connection | H1: Commissioning | I1: Owners costs & PM
A2: Provisions | B2: x | C2: x | D2: x | E2: x | F2: x | G2: x | H2: x | I2: x
A3: Duration | D3: x | H3: x | I3: x
A4: Q_Civils | E4: x
A5: Q_Elec | F5: x
A6: Q_Grid | G6: x
A7: R_Turbine | C7: x
A8: FX | C8: x | F8: x
A9: R_Concrete | B9: x | C9: x | D9: x | E9: x | F9: x | G9: x | H9: x | I9: x
A10: R_Steel | B10: x | C10: x | D10: x | E10: x | F10: x | G10: x | H10: x | I10: x
A11: R_General | B11: x | C11: x | D11: x | E11: x | F11: x | G11: x | H11: x | I11: x
A12: R_Plant | B12: x | C12: x | D12: x | E12: x | F12: x | G12: x | H12: x | I12: x
A13: R_Subcon | B13: x | D13: x | F13: x | G13: x | H13: x
A14: R_Staff | B14: x | C14: x | D14: x | E14: x | F14: x | G14: x | H14: x | I14: x
A15: R_Labour | B15: x | C15: x | D15: x | E15: x | F15: x | G15: x | H15: x | I15: x

Sheet Layer1_Correlation
A1: Corr_Mode | B1: elicited | C1: (zero | elicited | one)
A2: PSD_Status | B2: valid | C2: (reader recomputes via Corr_flag)
A4: Factor | B4: R_Turbine | C4: FX | D4: R_Concrete | E4: R_Steel | F4: R_General | G4: R_Plant | H4: R_Subcon
A5: R_Turbine | B5: 1
A6: FX | B6: 0.3 | C6: 1
A7: R_Concrete | B7: 0.3 | C7: 0.1 | D7: 1
A8: R_Steel | B8: 0.4 | C8: 0.2 | D8: 0.5 | E8: 1
A9: R_General | B9: 0.3 | C9: 0.3 | D9: 0.4 | E9: 0.4 | F9: 1
A10: R_Plant | B10: 0.2 | C10: 0.1 | D10: 0.3 | E10: 0.3 | F10: 0.3 | G10: 1
A11: R_Subcon | B11: 0.2 | C11: 0.1 | D11: 0.3 | E11: 0.3 | F11: 0.4 | G11: 0.3 | H11: 1

Sheet Reference (xlwings)
A1: xlwings Lite - requirements & code (paste-once)
A3: Requirements (xlwings Lite -> Environment)
A4: numpy
A5: scipy
A6: Pyodide runtime: 314.0.1 (ratified Q4; do not float)
A8: How to load the model code
A9: Generate the pasteable script with python tools/make_qra_xlwings.py -> dist/qra_xlwings_combined.py, then paste it into the xlwings Lite editor. That generated file is the source of truth (byte-parity gated to the repo engine); do not hand-edit. The text below is a human-readable convenience copy of the @script entry points only.
A11: Buttons (xlwings Lite task pane - one per @script)
A12: Run Simulation | B12: cost-QRA at the interactive count (Settings B1 / Set_iterations, default 25,000).
A13: Run Simulation 100k | B13: cost-QRA at the on-demand 100,000 count (Settings B5 / Set_iterations_max) - the deliverable run.
A14: Validate Contract | B14: self-check the named-range contract + version + methodology; writes PASS/FAIL to Out_validation.
A16: src/tier1_xlwings_shell.py (@script source - convenience copy)
A17: """QRAXL-01 Tier-1 xlwings Lite shell (front-end I/O layer).
A19: The @script entry point the xlwings Lite runtime calls with the open workbook.
A20: It reads the contract-v2 register via xlwings ranges, feeds the cell GRIDS to the
A21: SHARED parser (``qra_register_parse`` - the same one Tier 2 uses, so Tier-1 ==
A22: Tier-2 on the read side by construction), then runs ``qra_core`` and writes the
A23: P-curve back.
A25: The @script is a THIN I/O wrapper over the headless-testable
A26: ``tier1_headless.run_headless`` (read ranges -> call the headless run -> write
A27: ranges), mirroring RF-01 (rf_headless.py is the runner, shell_xlwings.py the
A28: I/O). CI covers the compute + formatting; only the literal xlwings range read/
A29: write is Excel-only. ``qra_core``, the parser and the resolver stay Pyodide-
... A266: ["PASS" if ok else "FAIL"], [message]]

Sheet Handoff Prompt
A1: Handoff Prompt - read this tab, then execute it
A3: THE PROMPT (paste this into Claude Code, nothing else)
A5: Read the "Handoff Prompt" tab of dist/wind_register.xlsx with openpyxl and execute it.
A7: Everything below is the brief. It is also valid markdown - if you prefer a repo file,
A8: save this column as docs/POLISH_HANDOFF.md and the prompt becomes:
A9: Read docs/POLISH_HANDOFF.md and execute it.
A11: ===============================================================================================
A12: # CONTEXT
A13: ===============================================================================================
A15: This workbook is a cost-QRA register generated by this repo. Its structure and model logic are
A16: yours. Its CHARTS and FORMATTING were designed by hand in Excel and must be turned into a
A17: reproducible build step, so they survive the next regeneration.
... A398: ===============================================================================================

Sheet Build Log
A1: Build Log - presentation layer spec (rendered from config/polish_spec.yaml)
A2: Generated. Do not hand-edit - edit the YAML and re-run tools/register_polish.py.
A4: Spec version | B4: polish-v02
A5: Applies to | B5: wind_register.xlsx / register contract v1.4
A6: Run order | B6: LAST - after scaffold, after Simulation is populated
A7: Idempotent | B7: TRUE
A9: # | B9: Step | C9: Target sheet | D9: Range / object | E9: Action | F9: Detail / value | G9: Why
A10: 1 | B10: Unprotect workbook structure | C10: (workbook) | D10: workbook.protection | E10: unprotect | F10: No password | G10: REG04 locks structure; sheets cannot be added until released
A11: 2 | B11: Create Charts sheet | C11: Charts | D11: (sheet) | E11: add / recreate | F11: position 1, tabColor navy, gridlines off | G11: Dashboard tab; keeps protected machine tabs untouched
A12: 3 | B12: Title block | C12: Charts | D12: A1:A2 | E12: write text | F12: A1 title 14pt bold navy; A2 provenance note 9pt italic grey. A1 is a FORMULA on Set_ProjectName / Set_ProjectNumber, not the literal project string - the polish layer is shared across projects and must not carry a project identifier. | G12: Reader knows the charts are generated, not hand-made
A13: 4 | B13: Tornado helper - tie-break key | C13: Charts | D13: V3:V37 | E13: formula | F13: ='EMV & Mode Analysis'!B12-ROW()/1000000 (filled down) | G13: Breaks duplicate EMV values so LARGE/MATCH ranks uniquely
A14: 5 | B14: Tornado helper - rank | C14: Charts | D14: R3:R17 | E14: formula | F14: R3 = 1 literal; R4:R17 = previous + 1 | G14: Top-15 rank index that steps 6 and 7 LARGE() against
A15: 6 | B15: Tornado helper - label | C15: Charts | D15: S3:S17 | E15: formula | F15: INDEX/MATCH on LARGE of the tie-break key | G15: Risk description for the ranked EMV
A16: 7 | B16: Tornado helper - value | C16: Charts | D16: T3:T17 | E16: formula | F16: Untie-broken EMV for display, money format | G16: The tie-break key in V is offset by ROW()/1e6 and must never be charted
A17: 8 | B17: S-curve helper | C17: Charts | D17: X3:Y103 | E17: formula | F17: X = Simulation!E (money), Y = Simulation!D (0%) | G17: Scatter needs X (cost) LEFT of Y (prob); the source has them reversed
A18: 9 | B18: P-curve helper | C18: Charts | D18: AA3:AB21 | E18: formula | F18: AA is TEXT ("P"&level); AB is the cost | G18: Numeric P-level charts as a SERIES; text forces a category axis
A19: 10 | B19: Sensitivity helper | C19: Charts | D19: AD3:AG21 | E19: formula | F19: AD is TEXT; AE/AF/AG = Simulation J/K/L (rho=0 / elicited / rho=1) | G19: Same category fix; keeps the three rho series contiguous
A20: 60 | B20: Helper block headings | C20: Charts | D20: R1:AG2 | E20: write text | F20: Row 1 = block captions (9pt bold), row 2 = the column headings the charts read as SERIES TITLES via titles_from_data. Undocumented in the original Build Log but load-bearing: without row 2 every series is named "Series1". Ordered here, out of numeric sequence, because the chart steps that follow depend on it. | G20: Series names come from row 2; block captions make the collapsed outline legible
A21: 11 | B21: Chart: S-curve | C21: Charts | D21: chart_scurve | E21: add xyScatterLinesNoMarkers | F21: src Charts!X2:Y103; pos A4; legend off | G21: Cumulative cost distribution - primary QRA output
... A70: 61 | B70: TOC tab inventory + cell-type legend | C70: TOC & Instructions | D70: the "Tabs, in the order you fill them (auto-generated from the sheet inventory)" block | E70: add / recreate | F70: IMPLEMENTED 2026-07-30. Rebuilds the inventory from the ACTUAL sheet list and restores the cell-type legend beneath it. Fixes real data loss: when the generated tabs were added to the inventory by hand the rows were OVERWRITTEN rather than inserted, destroying "Cell-type legend" and the "input" and "calc" entries - so the legend that rule 2 depends on no longer explained blue or black font. That edit is the only change in this workbook's history with no Build Log entry, which is exactly why it went unnoticed. Existing descriptions are preserved; descriptions: only supplies text for tabs that have none. Rows are inserted or deleted to fit, so Set_ProjectName..Set_IssueDate move - the op re-points every TOC-scoped defined name and refuses to complete unless each still resolves to its original value. | G70: The TOC is the reader's entry point and the home of the cell-type legend. Hand-editing it is what broke it; regenerating from the sheet list is the only fix that does not repeat the mistake.

Sheet Polish Inbox
A1: Polish Inbox - pending presentation-layer amendments
A2: ONE-WAY QUEUE. Append changes here; register_polish.py merges them into config/polish_spec.yaml. Never edit the rendered spec on Reference (polish), and never hand-format cells instead of raising a row here.
A11: ID | B11: Raised | C11: Author | D11: Target sheet | E11: Change (human-readable) | F11: op: payload (YAML, 2-space indent) | G11: Status | H11: Merged in
A12: INB-001 | B12: 2026-09-08 | C12: Claude (Excel) | D12: Charts | E12: EXAMPLE ROW - shows the required shape. Set Status to pending to activate, or leave as example to keep it inert. | F12: kind: header sheet: Charts ref: A1 | G12: example | H12: -

Sheet Reference (polish)
A1: Polish reference - the op vocabulary (GENERATED from the code - do not edit)
A3: Rendered by tools/register_polish.py at spec polish-v02.
A4: The repo is canonical: config/polish_spec.yaml holds the steps, this tab only
A5: describes what a step may contain. Editing here has no effect.
A7: HOW TO REQUEST A CHANGE
A8: Add a row to the Polish Inbox tab with Status = pending and an op: payload
A9: built from the table below. Do NOT hand-format cells - the next build
A10: regenerates them and your work is silently discarded.
A11: An invalid payload is rejected in place, with the reason written into the
A12: 'Merged in' column. It never reaches the spec.
A14: WHAT THE POLISH LAYER MAY CHANGE
A15: fill, column width, number format, alignment, freeze panes, column grouping,
... A74: the payload empty; the row will be rejected, which is the correct outcome.
